fear_data/__init__.py
fear_data/expt_config.py
fear_data/fc_data.py
fear_data/fc_data_utils.py
fear_data/fc_plot.py
fear_data/fc_plot_utils.py
fear_data/save_data.py
fear_data-0.1.1.dist-info/LICENSE
fear_data-0.1.1.dist-info/WHEEL
fear_data-0.1.1.dist-info/METADATA
fear_data-0.1.1.dist-info/RECORD
