Metadata-Version: 2.1
Name: fear-data
Version: 0.1.1
Summary: Python package for data analysis collected from Med-Associates VideoFreeze software.
Home-page: https://github.com/kpuhger/fear_data
License: MIT
Author: Kyle
Author-email: krpuhger@gmail.com
Requires-Python: >=3.9,<3.11
Classifier: License :: OSI Approved :: MIT License
Classifier: Programming Language :: Python :: 3
Classifier: Programming Language :: Python :: 3.10
Classifier: Programming Language :: Python :: 3.9
Requires-Dist: PyYAML (>=6.0,<7.0)
Requires-Dist: matplotlib (>=3.5.2,<4.0.0)
Requires-Dist: numpy (>=1.23.1,<2.0.0)
Requires-Dist: pandas (>=1.4.3,<2.0.0)
Requires-Dist: pingouin (>=0.5.2,<0.6.0)
Requires-Dist: ruamel.yaml (>=0.17.21,<0.18.0)
Requires-Dist: scipy (>=1.8.1,<2.0.0)
Requires-Dist: seaborn (>=0.11.2,<0.12.0)
Project-URL: Repository, https://github.com/kpuhger/fear_data
